phenom/__init__.py
phenom/credentials/__init__.py
phenom/credentials/api_client.py
phenom/credentials/authorization.py
phenom/credentials/configuration.py
phenom/credentials/get_token.py
phenom/credentials/rest.py
phenom/prediction/__init__.py
phenom/prediction/api/__init__.py
phenom/prediction/api/prediction_api.py
phenom/prediction/models/__init__.py
phenom/prediction/models/bad_request.py
phenom/prediction/models/error_response.py
phenom/prediction/models/fyf_skill_request.py
phenom/prediction/models/fyf_skill_response.py
phenom/prediction/models/skill_result.py
phenom/prediction/models/skill_results.py
phenom/resumeparser/__init__.py
phenom/resumeparser/api/__init__.py
phenom/resumeparser/api/resume_parsing_api.py
phenom/resumeparser/models/__init__.py
phenom/resumeparser/models/error_response.py
phenom/resumeparser/models/error_response_errors.py
phenom/resumeparser/models/resume_file_request.py
phenom/resumeparser/models/resume_request.py
phenom/resumeparser/models/resume_response.py
phenom/resumeparser/models/resume_response_data.py
phenom/resumeparser/models/resume_response_data_resumedata.py
phenom/resumeparser/models/resume_response_data_resumedata_educationhisory.py
phenom/resumeparser/models/resume_response_data_resumedata_experiencesummary.py
phenom/resumeparser/models/resume_response_data_resumedata_internetaddress.py
phenom/resumeparser/models/resume_response_data_resumedata_mobile.py
phenom/resumeparser/models/resume_response_data_resumedata_personname.py
phenom/resumeparser/models/resume_response_data_resumedata_postaladdress.py
phenom/resumeparser/models/resume_response_data_resumedata_skilltaxonomy.py
phenom/resumeparser/models/resume_response_data_resumedata_workhistory.py
hemanth-0.0.34.dist-info/LICENSE
hemanth-0.0.34.dist-info/METADATA
hemanth-0.0.34.dist-info/WHEEL
hemanth-0.0.34.dist-info/top_level.txt
hemanth-0.0.34.dist-info/RECORD
