Metadata-Version: 2.1
Name: hemanth
Version: 0.0.34
Summary: hemanth
Author: hemanth
Author-email: 8297991468h@gmail.com
Keywords: arithmetic,math,mathematics,python tutorial,avi upadhyay
Classifier: Development Status :: 1 - Planning
Classifier: Intended Audience :: Developers
Classifier: Programming Language :: Python :: 3
Classifier: Operating System :: Unix
Classifier: Operating System :: MacOS :: MacOS X
Classifier: Operating System :: Microsoft :: Windows
License-File: LICENSE
